mlre/__init__.py
mlre/version.py
mlre/radar/__init__.py
mlre/radar/radar_api_client.py
mlre/radar/radar_api_server.py
mlre/radar/radar_app.py
mlre/radar/radar_common.py
mlre/radar/radar_database.py
mlre/radar/radar_frontend.py
mlre/radar/radar_session.py
mlre-0.4.0.dist-info/LICENSE
mlre-0.4.0.dist-info/METADATA
mlre-0.4.0.dist-info/WHEEL
mlre-0.4.0.dist-info/top_level.txt
mlre-0.4.0.dist-info/RECORD
