Metadata-Version: 2.1
Name: mlre
Version: 0.4.0
Summary: Machine Learning Research Environment
Home-page: https://github.com/cabrust/mlre
Author: Clemens-Alexander Brust
Author-email: cabrust@pm.me
License: UNKNOWN
Platform: UNKNOWN
Classifier: Programming Language :: Python :: 3
Classifier: Operating System :: OS Independent
Classifier: License :: OSI Approved :: BSD License
Requires-Python: >=3.7
Requires-Dist: requests (==2.22.0)
Requires-Dist: Flask (==1.1.1)
